pydashboard/__init__.py
pydashboard/pydashboard_main.py
pydashboard/pydashboard_server.py
pydashboard/containers/__init__.py
pydashboard/containers/basemodule.py
pydashboard/containers/tablemodule.py
pydashboard/containers/vstack.py
pydashboard/modules/apcupsd.py
pydashboard/modules/clock.py
pydashboard/modules/cmdrunner.py
pydashboard/modules/demo.py
pydashboard/modules/diskusage.py
pydashboard/modules/docker.py
pydashboard/modules/feedreader.py
pydashboard/modules/homeassistant.py
pydashboard/modules/jellyfin.py
pydashboard/modules/libvirt.py
pydashboard/modules/nut.py
pydashboard/modules/octoprint.py
pydashboard/modules/plugin.py
pydashboard/modules/qbittorrent.py
pydashboard/modules/resourceusage.py
pydashboard/modules/systemctl.py
pydashboard/modules/text.py
pydashboard/modules/textfile.py
pydashboard/modules/uptime.py
pydashboard/modules/vstack.py
pydashboard/modules/weather.py
pydashboard/utils/__init__.py
pydashboard/utils/bars.py
pydashboard/utils/lists.py
pydashboard/utils/numbers.py
pydashboard/utils/ssh.py
pydashboard/utils/strings.py
pydashboard/utils/types.py
pydashboard/utils/units.py
pydashboard-1.2.4.dist-info/METADATA
pydashboard-1.2.4.dist-info/WHEEL
pydashboard-1.2.4.dist-info/entry_points.txt
pydashboard-1.2.4.dist-info/licenses/LICENSE.txt
pydashboard-1.2.4.dist-info/RECORD
